Metadata-Version: 1.1
Name: ghoroghipy
Version: 0.0.1
Summary: ways that you can contact me
Home-page: UNKNOWN
Author: Amir Hosein Ghoroghi
Author-email: sahgh313@gmail.com
License: MIT
Keywords: ghoroghi
Platform: UNKNOWN
Classifier: Development Status :: 5 - Production/Stable
Classifier: Intended Audience :: Education
Classifier: Operating System :: Microsoft :: Windows :: Windows 10
Classifier: License :: OSI Approved :: MIT License
Classifier: Programming Language :: Python :: 3
